handpick/__init__.py
handpick/core.py
handpick-0.16.0.dist-info/LICENSE
handpick-0.16.0.dist-info/METADATA
handpick-0.16.0.dist-info/WHEEL
handpick-0.16.0.dist-info/RECORD
